dash_pdf/_DashPdf.py
dash_pdf/__init__.py
dash_pdf/_imports_.py
dash_pdf/dash_pdf.min.js
dash_pdf/dash_pdf.min.js.map
dash_pdf/metadata.json
dash_pdf/package-info.json
dash_pdf/pdf.py
dash_pdf-0.0.1.dist-info/LICENSE
dash_pdf-0.0.1.dist-info/METADATA
dash_pdf-0.0.1.dist-info/WHEEL
dash_pdf-0.0.1.dist-info/top_level.txt
dash_pdf-0.0.1.dist-info/RECORD
